gifing/__init__.py
gifing/colors.py
gifing/main.py
gifing-0.1.1.dist-info/licenses/LICENSE
gifing-0.1.1.dist-info/METADATA
gifing-0.1.1.dist-info/WHEEL
gifing-0.1.1.dist-info/top_level.txt
gifing-0.1.1.dist-info/RECORD
