Metadata-Version: 2.4
Name: gifing
Version: 0.1.1
Summary: A lightweight python tool for creating GIF
Author-email: Joseph Barbier <joseph.barbierdarnal@gmail.com>
License-Expression: MIT
Project-URL: Homepage, https://y-sunflower.github.io/gifing/
Project-URL: Issues, https://github.com/y-sunflower/gifing/issues
Project-URL: Documentation, https://y-sunflower.github.io/gifing/
Project-URL: Repository, https://github.com/y-sunflower/gifing
Keywords: GIF,image
Classifier: Programming Language :: Python :: 3
Classifier: Operating System :: OS Independent
Classifier: Development Status :: 4 - Beta
Requires-Python: >=3.9
License-File: LICENSE
Requires-Dist: imageio>=2.37.0
Dynamic: license-file
